terrayml/.env.example
terrayml/__init__.py
terrayml/generator.py
terrayml/loader.py
terrayml/py.typed
terrayml/terrayml.py
terrayml/utilities.py
terrayml/file_templates/api_gateway_module.tf.txt
terrayml/file_templates/backend_main.tf.txt
terrayml/file_templates/cognito_module.tf.txt
terrayml/file_templates/dynamodb_module.tf.txt
terrayml/file_templates/ecs_module.tf.txt
terrayml/file_templates/event_bridge_module.tf.txt
terrayml/file_templates/lambda_module.tf.txt
terrayml/file_templates/main.tf.txt
terrayml/file_templates/s3_module.tf.txt
terrayml/file_templates/terraform.tfvars.txt
terrayml/file_templates/variables.tf.txt
terrayml/file_templates/vpc_module.tf.txt
terrayml/mappings/api_gateway.py
terrayml/mappings/api_gateway_lambda.py
terrayml/mappings/cognito_identity_pool.py
terrayml/mappings/cognito_user_pool.py
terrayml/mappings/dynamodb_table.py
terrayml/mappings/ecs_application_load_balancer.py
terrayml/mappings/ecs_capacity_provider.py
terrayml/mappings/ecs_cluster.py
terrayml/mappings/ecs_service.py
terrayml/mappings/ecs_task_definition.py
terrayml/mappings/event_bridge_bus.py
terrayml/mappings/event_bridge_rule.py
terrayml/mappings/lambda_event.py
terrayml/mappings/lambda_function.py
terrayml/mappings/s3_bucket.py
terrayml/mappings/vpc.py
terrayml/modules/api_gateway/api_path_management.tf
terrayml/modules/api_gateway/cors.tf
terrayml/modules/api_gateway/main.tf
terrayml/modules/api_gateway/providers.tf
terrayml/modules/api_gateway/variables.tf
terrayml/modules/cognito/main.tf
terrayml/modules/cognito/providers.tf
terrayml/modules/cognito/variables.tf
terrayml/modules/dynamodb/main.tf
terrayml/modules/dynamodb/providers.tf
terrayml/modules/dynamodb/variables.tf
terrayml/modules/ecs/data_ec2_ami.tf
terrayml/modules/ecs/ecs_capacity_provider.tf
terrayml/modules/ecs/ecs_cluster.tf
terrayml/modules/ecs/ecs_instance_role.tf
terrayml/modules/ecs/ecs_service.tf
terrayml/modules/ecs/ecs_task_definition.tf
terrayml/modules/ecs/load_balancer.tf
terrayml-0.99.dist-info/LICENSE
terrayml-0.99.dist-info/METADATA
terrayml-0.99.dist-info/WHEEL
terrayml-0.99.dist-info/entry_points.txt
terrayml-0.99.dist-info/top_level.txt
terrayml-0.99.dist-info/RECORD
