Metadata-Version: 2.1
Name: terrayml
Version: 0.99
Summary: This is Terrayml.
Author: Warren Ezra Bruce Jaudian
Author-email: webpjaudian@gmail.com
License: MIT
License-File: LICENSE
Requires-Dist: awscli
Requires-Dist: Click
Requires-Dist: PyYAML
Requires-Dist: python-dotenv
